Metadata-Version: 1.1
Name: django-text
Version: 1.7.6
Summary: Intuitive text editing for humans using Django.
Home-page: https://github.com/antonagestam/django-text/
Author: Anton Agestam
Author-email: msn@antonagestam.se
License: The MIT License (MIT)
Platform: UNKNOWN
Classifier: Programming Language :: Python :: 2.7
Classifier: Programming Language :: Python :: 3
